ezLineNotify/__init__.py
ezLineNotify/main.py
ezLineNotify-0.0.0.5.dist-info/LICENSE
ezLineNotify-0.0.0.5.dist-info/METADATA
ezLineNotify-0.0.0.5.dist-info/WHEEL
ezLineNotify-0.0.0.5.dist-info/top_level.txt
ezLineNotify-0.0.0.5.dist-info/RECORD
